tetris_engine-0.3.4.dist-info/METADATA
tetris_engine-0.3.4.dist-info/WHEEL
tetris_engine-0.3.4.dist-info/license_files/LICENSE
tetris_engine_backend/__init__.py
tetris_engine_backend/tetris_engine_backend.cpython-37m-x86_64-linux-gnu.so
tetris_engine-0.3.4.dist-info/RECORD
