Metadata-Version: 2.1
Name: tetris_engine
Version: 0.3.4
License-File: LICENSE
Summary: A tetris engine written in rust
